setup.py
quickbase2/__init__.py
quickbase2.egg-info/PKG-INFO
quickbase2.egg-info/SOURCES.txt
quickbase2.egg-info/dependency_links.txt
quickbase2.egg-info/not-zip-safe
quickbase2.egg-info/top_level.txt