Metadata-Version: 1.0
Name: quickbase2
Version: 0.1
Summary: quickbase sdk python package
Home-page: http://github.com/Evoluto/quickbas-sdk-python
Author: unknown
Author-email: support@quickbase.com
License: MIT
Platform: UNKNOWN
